pyoche/__init__.py
pyoche/array.py
pyoche/dataset.py
pyoche/lazy_dataset.py
pyoche/sample.py
pyoche/ml/__init__.py
pyoche/ml/lazy_ml_dataset.py
pyoche/ml/ml_dataset.py
pyoche/ml/ml_sample.py
pyoche/ml/normalize.py
pyoche/structures/structure.py
pyoche/utils/funcs.py
pyoche/utils/harmonizers.py
pyoche/utils/ptyping.py
pyoche-0.1.3.dist-info/LICENSE
pyoche-0.1.3.dist-info/METADATA
pyoche-0.1.3.dist-info/WHEEL
pyoche-0.1.3.dist-info/top_level.txt
pyoche-0.1.3.dist-info/RECORD
